siftapi/__init__.py
siftapi/exceptions.py
siftapi/utils.py
siftapi/version.py
siftapi-1.1.0.dist-info/METADATA
siftapi-1.1.0.dist-info/RECORD
siftapi-1.1.0.dist-info/WHEEL
siftapi-1.1.0.dist-info/top_level.txt
