Metadata-Version: 2.1
Name: siftapi
Version: 1.1.0
Summary: A Python wrapper for Edison Sift API
Home-page: http://developer.edison.tech
Author: Edison
Author-email: developer@edison.tech
License: MIT
Keywords: email easilydo sift
Platform: UNKNOWN
Requires-Dist: requests
